parser_notam_package/__init__.py
parser_notam_package/json_schema_notam.py
parser_notam_package/parser_notam_package.py
parser_notam_package/schema.py
parser_notam_package/ICAO_dict/ICAO_abbr.py
parser_notam_package/ICAO_dict/ICAO_entity.py
parser_notam_package/ICAO_dict/ICAO_location.py
parser_notam_package/ICAO_dict/ICAO_status.py
parser_notam_package/ICAO_dict/__init__.py
parser_notam_package-0.4.1.dist-info/METADATA
parser_notam_package-0.4.1.dist-info/WHEEL
parser_notam_package-0.4.1.dist-info/top_level.txt
parser_notam_package-0.4.1.dist-info/RECORD
