Metadata-Version: 2.1
Name: parser-notam-package
Version: 0.4.1
Summary: A Python package to parse and validate NOTAM messages     
Home-page: https://github.com/hungthinhnguyen2912/notam_parser
License: UNKNOWN
Platform: UNKNOWN
Requires-Dist: jsonschema
